mix_python_sdk/__init__.py
mix_python_sdk/_version.py
mix_python_sdk/authentication.py
mix_python_sdk/basesdk.py
mix_python_sdk/files.py
mix_python_sdk/health.py
mix_python_sdk/helpers.py
mix_python_sdk/httpclient.py
mix_python_sdk/internal.py
mix_python_sdk/messages.py
mix_python_sdk/permissions.py
mix_python_sdk/preferences_sdk.py
mix_python_sdk/py.typed
mix_python_sdk/sdk.py
mix_python_sdk/sdkconfiguration.py
mix_python_sdk/sessions.py
mix_python_sdk/streaming.py
mix_python_sdk/system.py
mix_python_sdk/tool_models.py
mix_python_sdk/tools.py
mix_python_sdk/_hooks/__init__.py
mix_python_sdk/_hooks/registration.py
mix_python_sdk/_hooks/sdkhooks.py
mix_python_sdk/_hooks/types.py
mix_python_sdk/errors/__init__.py
mix_python_sdk/errors/errorresponse.py
mix_python_sdk/errors/mixdefaulterror.py
mix_python_sdk/errors/mixerror.py
mix_python_sdk/errors/no_response_error.py
mix_python_sdk/errors/responsevalidationerror.py
mix_python_sdk/models/__init__.py
mix_python_sdk/models/backendmessage.py
mix_python_sdk/models/callback.py
mix_python_sdk/models/callbackresultdata.py
mix_python_sdk/models/cancelsessionprocessingop.py
mix_python_sdk/models/coretoolname.py
mix_python_sdk/models/createsessionop.py
mix_python_sdk/models/deletecredentialsop.py
mix_python_sdk/models/deletesessionfileop.py
mix_python_sdk/models/deletesessionop.py
mix_python_sdk/models/denypermissionop.py
mix_python_sdk/models/exportmessage.py
mix_python_sdk/models/exportsession.py
mix_python_sdk/models/exportsessionop.py
mix_python_sdk/models/exporttoolcall.py
mix_python_sdk/models/fileinfo.py
mix_python_sdk/models/forksessionop.py
mix_python_sdk/models/getauthstatusop.py
mix_python_sdk/models/getavailableprovidersop.py
mix_python_sdk/models/getcommandop.py
mix_python_sdk/models/getmessagehistoryop.py
mix_python_sdk/models/getoauthhealthop.py
mix_python_sdk/models/getpreferencesop.py
mix_python_sdk/models/getsessionfileop.py
mix_python_sdk/models/getsessionmessagesop.py
mix_python_sdk/models/getsessionop.py
mix_python_sdk-0.7.1.dist-info/METADATA
mix_python_sdk-0.7.1.dist-info/WHEEL
mix_python_sdk-0.7.1.dist-info/top_level.txt
mix_python_sdk-0.7.1.dist-info/RECORD
