Metadata-Version: 2.4
Name: mix-python-sdk
Version: 0.7.1
Summary: Python Client SDK Generated by Speakeasy.
Author: Speakeasy
Requires-Python: >=3.9.2
Requires-Dist: dotenv<0.10.0,>=0.9.9
Requires-Dist: httpcore>=1.0.9
Requires-Dist: httpx>=0.28.1
Requires-Dist: pydantic>=2.11.2
